{
  "generated_at": "2025-09-25T10:55:57.406759+00:00",
  "tasks": [
    {
      "task": "acoustic",
      "title": "HK acoustic CNN",
      "status": 0,
      "start_time": 1758797702,
      "end_time": 1758797735,
      "duration_seconds": 33,
      "metrics_path": "/Users/test/Code/drystate/projectK/nrw-ai/models/baseline/acoustic_cnn/metrics.json",
      "output_dir": "/Users/test/Code/drystate/projectK/nrw-ai/models/baseline/acoustic_cnn",
      "metrics": {
        "auroc": 0.7134502923976608,
        "auprc": 0.8593769021339495,
        "recall_at_fpr": 0.42105263157894735,
        "fpr_target": 0.1,
        "threshold": 0.5338390469551086
      }
    },
    {
      "task": "logger:yorkshire",
      "title": "Yorkshire logger XGBoost",
      "status": 0,
      "start_time": 1758797735,
      "end_time": 1758797736,
      "duration_seconds": 1,
      "metrics_path": "/Users/test/Code/drystate/projectK/nrw-ai/models/baseline/logger_xgb/yorkshire/metrics.json",
      "output_dir": "/Users/test/Code/drystate/projectK/nrw-ai/models/baseline/logger_xgb/yorkshire",
      "metrics": {
        "status": "skipped",
        "reason": "no_labelled_rows",
        "dataset": "yorkshire",
        "feature_path": "/Users/test/Code/drystate/projectK/nrw-ai/data/processed/yorkshire/yorkshire_logger_features.parquet",
        "total_rows": 0,
        "labelled_rows": 0
      }
    },
    {
      "task": "logger:wessex",
      "title": "Wessex logger XGBoost",
      "status": 0,
      "start_time": 1758797736,
      "end_time": 1758797737,
      "duration_seconds": 1,
      "metrics_path": "/Users/test/Code/drystate/projectK/nrw-ai/models/baseline/logger_xgb/wessex/metrics.json",
      "output_dir": "/Users/test/Code/drystate/projectK/nrw-ai/models/baseline/logger_xgb/wessex",
      "metrics": {
        "status": "skipped",
        "reason": "no_labelled_rows",
        "dataset": "wessex",
        "feature_path": "/Users/test/Code/drystate/projectK/nrw-ai/data/processed/wessex/wessex_logger_features.parquet",
        "total_rows": 0,
        "labelled_rows": 0
      }
    },
    {
      "task": "hydraulic",
      "title": "BattLeDIM hydraulic XGBoost",
      "status": 0,
      "start_time": 1758797737,
      "end_time": 1758797757,
      "duration_seconds": 20,
      "metrics_path": "/Users/test/Code/drystate/projectK/nrw-ai/models/baseline/hydraulic_xgb/metrics.json",
      "output_dir": "/Users/test/Code/drystate/projectK/nrw-ai/models/baseline/hydraulic_xgb",
      "metrics": {
        "auroc": 0.9999999614466323,
        "auprc": 0.9999999361887029,
        "recall_at_fpr": 1.0,
        "fpr_target": 0.1,
        "threshold": 0.5493361353874207
      }
    }
  ],
  "context": {
    "samples": null,
    "xgb_rounds": null,
    "output_base": "/Users/test/Code/drystate/projectK/nrw-ai/models",
    "parallel": false,
    "include_synthetic": false,
    "synthetic_ratio": null,
    "retries": 2,
    "retry_delay": 5,
    "start_time": 1758797702,
    "end_time": 1758797757
  }
}