{
  "generated_at": "2025-09-26T16:30:01.270917+00:00",
  "tasks": [
    {
      "task": "hydraulic",
      "title": "BattLeDIM hydraulic XGBoost",
      "status": 0,
      "start_time": 1758904178,
      "end_time": 1758904201,
      "duration_seconds": 23,
      "metrics_path": "/Users/test/Code/drystate/projectK/nrw-ai/models/baseline/hydraulic_xgb/metrics.json",
      "output_dir": "/Users/test/Code/drystate/projectK/nrw-ai/models/baseline/hydraulic_xgb",
      "metrics": {
        "auroc": 0.9990988490361176,
        "auprc": 0.9999534943890276,
        "recall_at_fpr": 0.9975479157283691,
        "fpr_target": 0.1,
        "threshold": 0.06829290837049484
      }
    }
  ],
  "context": {
    "samples": null,
    "xgb_rounds": null,
    "output_base": "/Users/test/Code/drystate/projectK/nrw-ai/models",
    "parallel": false,
    "include_synthetic": true,
    "synthetic_ratio": 0.2,
    "retries": 2,
    "retry_delay": 5,
    "start_time": 1758904178,
    "end_time": 1758904201
  }
}